vivarium_testing_utils/__about__.py
vivarium_testing_utils/__init__.py
vivarium_testing_utils/_version.py
vivarium_testing_utils/fuzzy_checker.py
vivarium_testing_utils-1.0.0.dist-info/LICENSE
vivarium_testing_utils-1.0.0.dist-info/METADATA
vivarium_testing_utils-1.0.0.dist-info/WHEEL
vivarium_testing_utils-1.0.0.dist-info/top_level.txt
vivarium_testing_utils-1.0.0.dist-info/RECORD
